{
    "%vlocity_namespace%__CalculationMatrixId__c": {
        "Name": "NamanTest",
        "VlocityDataPackType": "VlocityLookupMatchingKeyObject",
        "VlocityLookupRecordSourceKey": "%vlocity_namespace%__CalculationMatrix__c/NamanTest",
        "VlocityRecordSObjectType": "%vlocity_namespace%__CalculationMatrix__c"
    },
    "%vlocity_namespace%__CalculationMatrixId__r.Name": "NamanTest",
    "%vlocity_namespace%__CurrentStatus__c": "Active",
    "%vlocity_namespace%__EndDateTime__c": "",
    "%vlocity_namespace%__GlobalKey__c": "NamanTest V1",
    "%vlocity_namespace%__GroupKeyValue__c": "",
    "%vlocity_namespace%__MatrixUseLongOutput__c": false,
    "%vlocity_namespace%__Priority__c": 1,
    "%vlocity_namespace%__StartDateTime__c": "2023-07-17T09:59:38.000Z",
    "%vlocity_namespace%__SubGroupKeyValue__c": "",
    "%vlocity_namespace%__UseLongOutput__c": false,
    "%vlocity_namespace%__VersionNumber__c": 1,
    "Name": "NamanTest V1",
    "VlocityDataPackType": "SObject",
    "VlocityRecordSObjectType": "%vlocity_namespace%__CalculationMatrixVersion__c",
    "VlocityRecordSourceKey": "%vlocity_namespace%__CalculationMatrixVersion__c/1/%vlocity_namespace%__CalculationMatrix__c/NamanTest"
}