{
    "%vlocity_namespace%__Description__c": "",
    "%vlocity_namespace%__EffectiveFromDate__c": "",
    "%vlocity_namespace%__EffectiveUntilDate__c": "",
    "%vlocity_namespace%__GlobalKey__c": "29ace50d-d6bb-77eb-35d9-21879b55b1ca",
    "%vlocity_namespace%__IsActive__c": true,
    "%vlocity_namespace%__IsDefault__c": false,
    "%vlocity_namespace%__ObjectClassId__c": {
        "%vlocity_namespace%__GlobalKey__c": "63ba6ae5f8c257f7cdccc385d2a85dca",
        "VlocityDataPackType": "VlocityLookupMatchingKeyObject",
        "VlocityLookupRecordSourceKey": "%vlocity_namespace%__ObjectClass__c/63ba6ae5f8c257f7cdccc385d2a85dca",
        "VlocityRecordSObjectType": "%vlocity_namespace%__ObjectClass__c"
    },
    "%vlocity_namespace%__ObjectFacet__c": [
        {
            "%vlocity_namespace%__EffectiveFromDate__c": "",
            "%vlocity_namespace%__EffectiveUntilDate__c": "",
            "%vlocity_namespace%__FacetId__c": {
                "%vlocity_namespace%__GlobalKey__c": "5ceff4783b0f59f31b27417a7064a12c",
                "VlocityDataPackType": "VlocityLookupMatchingKeyObject",
                "VlocityLookupRecordSourceKey": "%vlocity_namespace%__UIFacet__c/5ceff4783b0f59f31b27417a7064a12c",
                "VlocityRecordSObjectType": "%vlocity_namespace%__UIFacet__c"
            },
            "%vlocity_namespace%__GlobalKey__c": "6b91763f-40b4-b1ad-7434-6f4d14e6f14d",
            "%vlocity_namespace%__IsActive__c": true,
            "%vlocity_namespace%__ObjectLayoutId__c": {
                "%vlocity_namespace%__GlobalKey__c": "29ace50d-d6bb-77eb-35d9-21879b55b1ca",
                "VlocityDataPackType": "VlocityMatchingKeyObject",
                "VlocityMatchingRecordSourceKey": "%vlocity_namespace%__ObjectLayout__c/29ace50d-d6bb-77eb-35d9-21879b55b1ca",
                "VlocityRecordSObjectType": "%vlocity_namespace%__ObjectLayout__c"
            },
            "%vlocity_namespace%__ObjectSection__c": [
                {
                    "%vlocity_namespace%__ColumnLayout__c": "2 Columns",
                    "%vlocity_namespace%__EffectiveFromDate__c": "",
                    "%vlocity_namespace%__EffectiveUntilDate__c": "",
                    "%vlocity_namespace%__GlobalKey__c": "d70e6a55-00c1-2e49-c25b-8e1bf7c38aec",
                    "%vlocity_namespace%__IsActive__c": true,
                    "%vlocity_namespace%__ObjectElement__c": [
                        {
                            "%vlocity_namespace%__AttributeId__c": "",
                            "%vlocity_namespace%__Column__c": "1",
                            "%vlocity_namespace%__EffectiveFromDate__c": "",
                            "%vlocity_namespace%__EffectiveUntilDate__c": "",
                            "%vlocity_namespace%__FieldApiName__c": "Name",
                            "%vlocity_namespace%__GlobalKey__c": "619b9eba-8beb-2f02-f423-09186b18794e",
                            "%vlocity_namespace%__IsActive__c": true,
                            "%vlocity_namespace%__IsRequired__c": true,
                            "%vlocity_namespace%__ObjectSectionId__c": {
                                "Name": "d70e6a55-00c1-2e49-c25b-8e1bf7c38aec",
                                "VlocityDataPackType": "VlocityMatchingKeyObject",
                                "VlocityMatchingRecordSourceKey": "%vlocity_namespace%__ObjectSection__c/d70e6a55-00c1-2e49-c25b-8e1bf7c38aec",
                                "VlocityRecordSObjectType": "%vlocity_namespace%__ObjectSection__c"
                            },
                            "%vlocity_namespace%__Sequence__c": 10,
                            "%vlocity_namespace%__Type__c": "Field",
                            "Name": "Product Name",
                            "VlocityDataPackType": "SObject",
                            "VlocityRecordSObjectType": "%vlocity_namespace%__ObjectElement__c",
                            "VlocityRecordSourceKey": "%vlocity_namespace%__ObjectElement__c/619b9eba-8beb-2f02-f423-09186b18794e"
                        },
                        {
                            "%vlocity_namespace%__AttributeId__c": "",
                            "%vlocity_namespace%__Column__c": "1",
                            "%vlocity_namespace%__EffectiveFromDate__c": "",
                            "%vlocity_namespace%__EffectiveUntilDate__c": "",
                            "%vlocity_namespace%__FieldApiName__c": "ProductCode",
                            "%vlocity_namespace%__GlobalKey__c": "7bc0191e-3378-ecc6-68c6-65199fbb63a0",
                            "%vlocity_namespace%__IsActive__c": true,
                            "%vlocity_namespace%__IsRequired__c": true,
                            "%vlocity_namespace%__ObjectSectionId__c": {
                                "Name": "d70e6a55-00c1-2e49-c25b-8e1bf7c38aec",
                                "VlocityDataPackType": "VlocityMatchingKeyObject",
                                "VlocityMatchingRecordSourceKey": "%vlocity_namespace%__ObjectSection__c/d70e6a55-00c1-2e49-c25b-8e1bf7c38aec",
                                "VlocityRecordSObjectType": "%vlocity_namespace%__ObjectSection__c"
                            },
                            "%vlocity_namespace%__Sequence__c": 20,
                            "%vlocity_namespace%__Type__c": "Field",
                            "Name": "Product Code",
                            "VlocityDataPackType": "SObject",
                            "VlocityRecordSObjectType": "%vlocity_namespace%__ObjectElement__c",
                            "VlocityRecordSourceKey": "%vlocity_namespace%__ObjectElement__c/7bc0191e-3378-ecc6-68c6-65199fbb63a0"
                        },
                        {
                            "%vlocity_namespace%__AttributeId__c": "",
                            "%vlocity_namespace%__Column__c": "1",
                            "%vlocity_namespace%__EffectiveFromDate__c": "",
                            "%vlocity_namespace%__EffectiveUntilDate__c": "",
                            "%vlocity_namespace%__FieldApiName__c": "Description",
                            "%vlocity_namespace%__GlobalKey__c": "f148b970-fbb9-80ea-ee61-3358143954cb",
                            "%vlocity_namespace%__IsActive__c": true,
                            "%vlocity_namespace%__IsRequired__c": false,
                            "%vlocity_namespace%__ObjectSectionId__c": {
                                "Name": "d70e6a55-00c1-2e49-c25b-8e1bf7c38aec",
                                "VlocityDataPackType": "VlocityMatchingKeyObject",
                                "VlocityMatchingRecordSourceKey": "%vlocity_namespace%__ObjectSection__c/d70e6a55-00c1-2e49-c25b-8e1bf7c38aec",
                                "VlocityRecordSObjectType": "%vlocity_namespace%__ObjectSection__c"
                            },
                            "%vlocity_namespace%__Sequence__c": 30,
                            "%vlocity_namespace%__Type__c": "Field",
                            "Name": "Product Description",
                            "VlocityDataPackType": "SObject",
                            "VlocityRecordSObjectType": "%vlocity_namespace%__ObjectElement__c",
                            "VlocityRecordSourceKey": "%vlocity_namespace%__ObjectElement__c/f148b970-fbb9-80ea-ee61-3358143954cb"
                        },
                        {
                            "%vlocity_namespace%__AttributeId__c": "",
                            "%vlocity_namespace%__Column__c": "1",
                            "%vlocity_namespace%__EffectiveFromDate__c": "",
                            "%vlocity_namespace%__EffectiveUntilDate__c": "",
                            "%vlocity_namespace%__FieldApiName__c": "%vlocity_namespace%__ObjectTypeId__c",
                            "%vlocity_namespace%__GlobalKey__c": "53845ba8-d16a-b908-5f37-17cc4e4f5475",
                            "%vlocity_namespace%__IsActive__c": true,
                            "%vlocity_namespace%__IsRequired__c": false,
                            "%vlocity_namespace%__ObjectSectionId__c": {
                                "Name": "d70e6a55-00c1-2e49-c25b-8e1bf7c38aec",
                                "VlocityDataPackType": "VlocityMatchingKeyObject",
                                "VlocityMatchingRecordSourceKey": "%vlocity_namespace%__ObjectSection__c/d70e6a55-00c1-2e49-c25b-8e1bf7c38aec",
                                "VlocityRecordSObjectType": "%vlocity_namespace%__ObjectSection__c"
                            },
                            "%vlocity_namespace%__Sequence__c": 40,
                            "%vlocity_namespace%__Type__c": "Field",
                            "Name": "Object Type",
                            "VlocityDataPackType": "SObject",
                            "VlocityRecordSObjectType": "%vlocity_namespace%__ObjectElement__c",
                            "VlocityRecordSourceKey": "%vlocity_namespace%__ObjectElement__c/53845ba8-d16a-b908-5f37-17cc4e4f5475"
                        },
                        {
                            "%vlocity_namespace%__AttributeId__c": "",
                            "%vlocity_namespace%__Column__c": "1",
                            "%vlocity_namespace%__EffectiveFromDate__c": "",
                            "%vlocity_namespace%__EffectiveUntilDate__c": "",
                            "%vlocity_namespace%__FieldApiName__c": "Family",
                            "%vlocity_namespace%__GlobalKey__c": "200bde49-3a4f-eef1-2d5a-73c6e56bfc65",
                            "%vlocity_namespace%__IsActive__c": true,
                            "%vlocity_namespace%__IsRequired__c": false,
                            "%vlocity_namespace%__ObjectSectionId__c": {
                                "Name": "d70e6a55-00c1-2e49-c25b-8e1bf7c38aec",
                                "VlocityDataPackType": "VlocityMatchingKeyObject",
                                "VlocityMatchingRecordSourceKey": "%vlocity_namespace%__ObjectSection__c/d70e6a55-00c1-2e49-c25b-8e1bf7c38aec",
                                "VlocityRecordSObjectType": "%vlocity_namespace%__ObjectSection__c"
                            },
                            "%vlocity_namespace%__Sequence__c": 50,
                            "%vlocity_namespace%__Type__c": "Field",
                            "Name": "Product Family",
                            "VlocityDataPackType": "SObject",
                            "VlocityRecordSObjectType": "%vlocity_namespace%__ObjectElement__c",
                            "VlocityRecordSourceKey": "%vlocity_namespace%__ObjectElement__c/200bde49-3a4f-eef1-2d5a-73c6e56bfc65"
                        },
                        {
                            "%vlocity_namespace%__AttributeId__c": "",
                            "%vlocity_namespace%__Column__c": "1",
                            "%vlocity_namespace%__EffectiveFromDate__c": "",
                            "%vlocity_namespace%__EffectiveUntilDate__c": "",
                            "%vlocity_namespace%__FieldApiName__c": "%vlocity_namespace%__SpecificationType__c",
                            "%vlocity_namespace%__GlobalKey__c": "19760a5c-aab5-bece-1251-c69a3a8d61fe",
                            "%vlocity_namespace%__IsActive__c": true,
                            "%vlocity_namespace%__IsRequired__c": false,
                            "%vlocity_namespace%__ObjectSectionId__c": {
                                "Name": "d70e6a55-00c1-2e49-c25b-8e1bf7c38aec",
                                "VlocityDataPackType": "VlocityMatchingKeyObject",
                                "VlocityMatchingRecordSourceKey": "%vlocity_namespace%__ObjectSection__c/d70e6a55-00c1-2e49-c25b-8e1bf7c38aec",
                                "VlocityRecordSObjectType": "%vlocity_namespace%__ObjectSection__c"
                            },
                            "%vlocity_namespace%__Sequence__c": 60,
                            "%vlocity_namespace%__Type__c": "Field",
                            "Name": "Specification Type",
                            "VlocityDataPackType": "SObject",
                            "VlocityRecordSObjectType": "%vlocity_namespace%__ObjectElement__c",
                            "VlocityRecordSourceKey": "%vlocity_namespace%__ObjectElement__c/19760a5c-aab5-bece-1251-c69a3a8d61fe"
                        },
                        {
                            "%vlocity_namespace%__AttributeId__c": "",
                            "%vlocity_namespace%__Column__c": "1",
                            "%vlocity_namespace%__EffectiveFromDate__c": "",
                            "%vlocity_namespace%__EffectiveUntilDate__c": "",
                            "%vlocity_namespace%__FieldApiName__c": "%vlocity_namespace%__SpecificationSubType__c",
                            "%vlocity_namespace%__GlobalKey__c": "dbaea949-9019-0313-a2ab-df3d079f2f3b",
                            "%vlocity_namespace%__IsActive__c": true,
                            "%vlocity_namespace%__IsRequired__c": false,
                            "%vlocity_namespace%__ObjectSectionId__c": {
                                "Name": "d70e6a55-00c1-2e49-c25b-8e1bf7c38aec",
                                "VlocityDataPackType": "VlocityMatchingKeyObject",
                                "VlocityMatchingRecordSourceKey": "%vlocity_namespace%__ObjectSection__c/d70e6a55-00c1-2e49-c25b-8e1bf7c38aec",
                                "VlocityRecordSObjectType": "%vlocity_namespace%__ObjectSection__c"
                            },
                            "%vlocity_namespace%__Sequence__c": 70,
                            "%vlocity_namespace%__Type__c": "Field",
                            "Name": "Specification Sub Type",
                            "VlocityDataPackType": "SObject",
                            "VlocityRecordSObjectType": "%vlocity_namespace%__ObjectElement__c",
                            "VlocityRecordSourceKey": "%vlocity_namespace%__ObjectElement__c/dbaea949-9019-0313-a2ab-df3d079f2f3b"
                        },
                        {
                            "%vlocity_namespace%__AttributeId__c": "",
                            "%vlocity_namespace%__Column__c": "1",
                            "%vlocity_namespace%__EffectiveFromDate__c": "",
                            "%vlocity_namespace%__EffectiveUntilDate__c": "",
                            "%vlocity_namespace%__FieldApiName__c": "%vlocity_namespace%__ProductSpecId__c",
                            "%vlocity_namespace%__GlobalKey__c": "8a48595e-ca3f-c68a-08d1-83c7b3f311e8",
                            "%vlocity_namespace%__IsActive__c": true,
                            "%vlocity_namespace%__IsRequired__c": false,
                            "%vlocity_namespace%__ObjectSectionId__c": {
                                "Name": "d70e6a55-00c1-2e49-c25b-8e1bf7c38aec",
                                "VlocityDataPackType": "VlocityMatchingKeyObject",
                                "VlocityMatchingRecordSourceKey": "%vlocity_namespace%__ObjectSection__c/d70e6a55-00c1-2e49-c25b-8e1bf7c38aec",
                                "VlocityRecordSObjectType": "%vlocity_namespace%__ObjectSection__c"
                            },
                            "%vlocity_namespace%__Sequence__c": 80,
                            "%vlocity_namespace%__Type__c": "Field",
                            "Name": "Product Spec",
                            "VlocityDataPackType": "SObject",
                            "VlocityRecordSObjectType": "%vlocity_namespace%__ObjectElement__c",
                            "VlocityRecordSourceKey": "%vlocity_namespace%__ObjectElement__c/8a48595e-ca3f-c68a-08d1-83c7b3f311e8"
                        },
                        {
                            "%vlocity_namespace%__AttributeId__c": "",
                            "%vlocity_namespace%__Column__c": "1",
                            "%vlocity_namespace%__EffectiveFromDate__c": "",
                            "%vlocity_namespace%__EffectiveUntilDate__c": "",
                            "%vlocity_namespace%__FieldApiName__c": "%vlocity_namespace%__Status__c",
                            "%vlocity_namespace%__GlobalKey__c": "118e8474-7718-7fff-f1ea-251c63b5a0f3",
                            "%vlocity_namespace%__IsActive__c": true,
                            "%vlocity_namespace%__IsRequired__c": false,
                            "%vlocity_namespace%__ObjectSectionId__c": {
                                "Name": "d70e6a55-00c1-2e49-c25b-8e1bf7c38aec",
                                "VlocityDataPackType": "VlocityMatchingKeyObject",
                                "VlocityMatchingRecordSourceKey": "%vlocity_namespace%__ObjectSection__c/d70e6a55-00c1-2e49-c25b-8e1bf7c38aec",
                                "VlocityRecordSObjectType": "%vlocity_namespace%__ObjectSection__c"
                            },
                            "%vlocity_namespace%__Sequence__c": 90,
                            "%vlocity_namespace%__Type__c": "Field",
                            "Name": "Status",
                            "VlocityDataPackType": "SObject",
                            "VlocityRecordSObjectType": "%vlocity_namespace%__ObjectElement__c",
                            "VlocityRecordSourceKey": "%vlocity_namespace%__ObjectElement__c/118e8474-7718-7fff-f1ea-251c63b5a0f3"
                        },
                        {
                            "%vlocity_namespace%__AttributeId__c": "",
                            "%vlocity_namespace%__Column__c": "2",
                            "%vlocity_namespace%__EffectiveFromDate__c": "",
                            "%vlocity_namespace%__EffectiveUntilDate__c": "",
                            "%vlocity_namespace%__FieldApiName__c": "%vlocity_namespace%__IsOrderable__c",
                            "%vlocity_namespace%__GlobalKey__c": "47bb3fac-e457-f7bc-e232-cae0cf07337e",
                            "%vlocity_namespace%__IsActive__c": true,
                            "%vlocity_namespace%__IsRequired__c": false,
                            "%vlocity_namespace%__ObjectSectionId__c": {
                                "Name": "d70e6a55-00c1-2e49-c25b-8e1bf7c38aec",
                                "VlocityDataPackType": "VlocityMatchingKeyObject",
                                "VlocityMatchingRecordSourceKey": "%vlocity_namespace%__ObjectSection__c/d70e6a55-00c1-2e49-c25b-8e1bf7c38aec",
                                "VlocityRecordSObjectType": "%vlocity_namespace%__ObjectSection__c"
                            },
                            "%vlocity_namespace%__Sequence__c": 100,
                            "%vlocity_namespace%__Type__c": "Field",
                            "Name": "Orderable",
                            "VlocityDataPackType": "SObject",
                            "VlocityRecordSObjectType": "%vlocity_namespace%__ObjectElement__c",
                            "VlocityRecordSourceKey": "%vlocity_namespace%__ObjectElement__c/47bb3fac-e457-f7bc-e232-cae0cf07337e"
                        },
                        {
                            "%vlocity_namespace%__AttributeId__c": "",
                            "%vlocity_namespace%__Column__c": "2",
                            "%vlocity_namespace%__EffectiveFromDate__c": "",
                            "%vlocity_namespace%__EffectiveUntilDate__c": "",
                            "%vlocity_namespace%__FieldApiName__c": "%vlocity_namespace%__Type__c",
                            "%vlocity_namespace%__GlobalKey__c": "683133dd-6aaa-7a8e-737d-16934a9c6f0c",
                            "%vlocity_namespace%__IsActive__c": true,
                            "%vlocity_namespace%__IsRequired__c": false,
                            "%vlocity_namespace%__ObjectSectionId__c": {
                                "Name": "d70e6a55-00c1-2e49-c25b-8e1bf7c38aec",
                                "VlocityDataPackType": "VlocityMatchingKeyObject",
                                "VlocityMatchingRecordSourceKey": "%vlocity_namespace%__ObjectSection__c/d70e6a55-00c1-2e49-c25b-8e1bf7c38aec",
                                "VlocityRecordSObjectType": "%vlocity_namespace%__ObjectSection__c"
                            },
                            "%vlocity_namespace%__Sequence__c": 110,
                            "%vlocity_namespace%__Type__c": "Field",
                            "Name": "Type",
                            "VlocityDataPackType": "SObject",
                            "VlocityRecordSObjectType": "%vlocity_namespace%__ObjectElement__c",
                            "VlocityRecordSourceKey": "%vlocity_namespace%__ObjectElement__c/683133dd-6aaa-7a8e-737d-16934a9c6f0c"
                        },
                        {
                            "%vlocity_namespace%__AttributeId__c": "",
                            "%vlocity_namespace%__Column__c": "2",
                            "%vlocity_namespace%__EffectiveFromDate__c": "",
                            "%vlocity_namespace%__EffectiveUntilDate__c": "",
                            "%vlocity_namespace%__FieldApiName__c": "%vlocity_namespace%__SubType__c",
                            "%vlocity_namespace%__GlobalKey__c": "6abd9738-d3cf-3787-b3e3-a5b92807092a",
                            "%vlocity_namespace%__IsActive__c": true,
                            "%vlocity_namespace%__IsRequired__c": false,
                            "%vlocity_namespace%__ObjectSectionId__c": {
                                "Name": "d70e6a55-00c1-2e49-c25b-8e1bf7c38aec",
                                "VlocityDataPackType": "VlocityMatchingKeyObject",
                                "VlocityMatchingRecordSourceKey": "%vlocity_namespace%__ObjectSection__c/d70e6a55-00c1-2e49-c25b-8e1bf7c38aec",
                                "VlocityRecordSObjectType": "%vlocity_namespace%__ObjectSection__c"
                            },
                            "%vlocity_namespace%__Sequence__c": 120,
                            "%vlocity_namespace%__Type__c": "Field",
                            "Name": "Sub Type",
                            "VlocityDataPackType": "SObject",
                            "VlocityRecordSObjectType": "%vlocity_namespace%__ObjectElement__c",
                            "VlocityRecordSourceKey": "%vlocity_namespace%__ObjectElement__c/6abd9738-d3cf-3787-b3e3-a5b92807092a"
                        },
                        {
                            "%vlocity_namespace%__AttributeId__c": "",
                            "%vlocity_namespace%__Column__c": "2",
                            "%vlocity_namespace%__EffectiveFromDate__c": "",
                            "%vlocity_namespace%__EffectiveUntilDate__c": "",
                            "%vlocity_namespace%__FieldApiName__c": "%vlocity_namespace%__VersionLabel__c",
                            "%vlocity_namespace%__GlobalKey__c": "a69d41ad-a52b-56f5-5eed-5401beda7bf3",
                            "%vlocity_namespace%__IsActive__c": true,
                            "%vlocity_namespace%__IsRequired__c": false,
                            "%vlocity_namespace%__ObjectSectionId__c": {
                                "Name": "d70e6a55-00c1-2e49-c25b-8e1bf7c38aec",
                                "VlocityDataPackType": "VlocityMatchingKeyObject",
                                "VlocityMatchingRecordSourceKey": "%vlocity_namespace%__ObjectSection__c/d70e6a55-00c1-2e49-c25b-8e1bf7c38aec",
                                "VlocityRecordSObjectType": "%vlocity_namespace%__ObjectSection__c"
                            },
                            "%vlocity_namespace%__Sequence__c": 130,
                            "%vlocity_namespace%__Type__c": "Field",
                            "Name": "Version Label",
                            "VlocityDataPackType": "SObject",
                            "VlocityRecordSObjectType": "%vlocity_namespace%__ObjectElement__c",
                            "VlocityRecordSourceKey": "%vlocity_namespace%__ObjectElement__c/a69d41ad-a52b-56f5-5eed-5401beda7bf3"
                        },
                        {
                            "%vlocity_namespace%__AttributeId__c": "",
                            "%vlocity_namespace%__Column__c": "2",
                            "%vlocity_namespace%__EffectiveFromDate__c": "",
                            "%vlocity_namespace%__EffectiveUntilDate__c": "",
                            "%vlocity_namespace%__FieldApiName__c": "%vlocity_namespace%__VersionStartDateTime__c",
                            "%vlocity_namespace%__GlobalKey__c": "b75432c0-c00c-31ac-d921-dcdb2e17e824",
                            "%vlocity_namespace%__IsActive__c": true,
                            "%vlocity_namespace%__IsRequired__c": false,
                            "%vlocity_namespace%__ObjectSectionId__c": {
                                "Name": "d70e6a55-00c1-2e49-c25b-8e1bf7c38aec",
                                "VlocityDataPackType": "VlocityMatchingKeyObject",
                                "VlocityMatchingRecordSourceKey": "%vlocity_namespace%__ObjectSection__c/d70e6a55-00c1-2e49-c25b-8e1bf7c38aec",
                                "VlocityRecordSObjectType": "%vlocity_namespace%__ObjectSection__c"
                            },
                            "%vlocity_namespace%__Sequence__c": 140,
                            "%vlocity_namespace%__Type__c": "Field",
                            "Name": "Version Start Date",
                            "VlocityDataPackType": "SObject",
                            "VlocityRecordSObjectType": "%vlocity_namespace%__ObjectElement__c",
                            "VlocityRecordSourceKey": "%vlocity_namespace%__ObjectElement__c/b75432c0-c00c-31ac-d921-dcdb2e17e824"
                        },
                        {
                            "%vlocity_namespace%__AttributeId__c": "",
                            "%vlocity_namespace%__Column__c": "2",
                            "%vlocity_namespace%__EffectiveFromDate__c": "",
                            "%vlocity_namespace%__EffectiveUntilDate__c": "",
                            "%vlocity_namespace%__FieldApiName__c": "%vlocity_namespace%__VersionEndDateTime__c",
                            "%vlocity_namespace%__GlobalKey__c": "d5eee399-f31f-11f0-82e5-6f038617c77a",
                            "%vlocity_namespace%__IsActive__c": true,
                            "%vlocity_namespace%__IsRequired__c": false,
                            "%vlocity_namespace%__ObjectSectionId__c": {
                                "Name": "d70e6a55-00c1-2e49-c25b-8e1bf7c38aec",
                                "VlocityDataPackType": "VlocityMatchingKeyObject",
                                "VlocityMatchingRecordSourceKey": "%vlocity_namespace%__ObjectSection__c/d70e6a55-00c1-2e49-c25b-8e1bf7c38aec",
                                "VlocityRecordSObjectType": "%vlocity_namespace%__ObjectSection__c"
                            },
                            "%vlocity_namespace%__Sequence__c": 150,
                            "%vlocity_namespace%__Type__c": "Field",
                            "Name": "Version End Date",
                            "VlocityDataPackType": "SObject",
                            "VlocityRecordSObjectType": "%vlocity_namespace%__ObjectElement__c",
                            "VlocityRecordSourceKey": "%vlocity_namespace%__ObjectElement__c/d5eee399-f31f-11f0-82e5-6f038617c77a"
                        },
                        {
                            "%vlocity_namespace%__AttributeId__c": "",
                            "%vlocity_namespace%__Column__c": "2",
                            "%vlocity_namespace%__EffectiveFromDate__c": "",
                            "%vlocity_namespace%__EffectiveUntilDate__c": "",
                            "%vlocity_namespace%__FieldApiName__c": "%vlocity_namespace%__HelpText__c",
                            "%vlocity_namespace%__GlobalKey__c": "05694a95-5587-cd68-3a77-4960ddf6cc14",
                            "%vlocity_namespace%__IsActive__c": true,
                            "%vlocity_namespace%__IsRequired__c": false,
                            "%vlocity_namespace%__ObjectSectionId__c": {
                                "Name": "d70e6a55-00c1-2e49-c25b-8e1bf7c38aec",
                                "VlocityDataPackType": "VlocityMatchingKeyObject",
                                "VlocityMatchingRecordSourceKey": "%vlocity_namespace%__ObjectSection__c/d70e6a55-00c1-2e49-c25b-8e1bf7c38aec",
                                "VlocityRecordSObjectType": "%vlocity_namespace%__ObjectSection__c"
                            },
                            "%vlocity_namespace%__Sequence__c": 160,
                            "%vlocity_namespace%__Type__c": "Field",
                            "Name": "Help Text",
                            "VlocityDataPackType": "SObject",
                            "VlocityRecordSObjectType": "%vlocity_namespace%__ObjectElement__c",
                            "VlocityRecordSourceKey": "%vlocity_namespace%__ObjectElement__c/05694a95-5587-cd68-3a77-4960ddf6cc14"
                        },
                        {
                            "%vlocity_namespace%__AttributeId__c": "",
                            "%vlocity_namespace%__Column__c": "2",
                            "%vlocity_namespace%__EffectiveFromDate__c": "",
                            "%vlocity_namespace%__EffectiveUntilDate__c": "",
                            "%vlocity_namespace%__FieldApiName__c": "%vlocity_namespace%__LifecycleStatus__c",
                            "%vlocity_namespace%__GlobalKey__c": "686e5835-45d1-a60b-d334-a9ef6d959a5b",
                            "%vlocity_namespace%__IsActive__c": true,
                            "%vlocity_namespace%__IsRequired__c": false,
                            "%vlocity_namespace%__ObjectSectionId__c": {
                                "Name": "d70e6a55-00c1-2e49-c25b-8e1bf7c38aec",
                                "VlocityDataPackType": "VlocityMatchingKeyObject",
                                "VlocityMatchingRecordSourceKey": "%vlocity_namespace%__ObjectSection__c/d70e6a55-00c1-2e49-c25b-8e1bf7c38aec",
                                "VlocityRecordSObjectType": "%vlocity_namespace%__ObjectSection__c"
                            },
                            "%vlocity_namespace%__Sequence__c": 170,
                            "%vlocity_namespace%__Type__c": "Field",
                            "Name": "Lifecycle Status",
                            "VlocityDataPackType": "SObject",
                            "VlocityRecordSObjectType": "%vlocity_namespace%__ObjectElement__c",
                            "VlocityRecordSourceKey": "%vlocity_namespace%__ObjectElement__c/686e5835-45d1-a60b-d334-a9ef6d959a5b"
                        },
                        {
                            "%vlocity_namespace%__AttributeId__c": "",
                            "%vlocity_namespace%__Column__c": "1",
                            "%vlocity_namespace%__EffectiveFromDate__c": "",
                            "%vlocity_namespace%__EffectiveUntilDate__c": "",
                            "%vlocity_namespace%__FieldApiName__c": "",
                            "%vlocity_namespace%__GlobalKey__c": "34329484-b7c5-8658-d2ce-86409be1583d",
                            "%vlocity_namespace%__IsActive__c": true,
                            "%vlocity_namespace%__IsRequired__c": false,
                            "%vlocity_namespace%__ObjectSectionId__c": {
                                "Name": "d70e6a55-00c1-2e49-c25b-8e1bf7c38aec",
                                "VlocityDataPackType": "VlocityMatchingKeyObject",
                                "VlocityMatchingRecordSourceKey": "%vlocity_namespace%__ObjectSection__c/d70e6a55-00c1-2e49-c25b-8e1bf7c38aec",
                                "VlocityRecordSObjectType": "%vlocity_namespace%__ObjectSection__c"
                            },
                            "%vlocity_namespace%__Sequence__c": 325,
                            "Name": "ATTRIBUTE-A133720",
                            "VlocityDataPackType": "SObject",
                            "VlocityRecordSObjectType": "%vlocity_namespace%__ObjectElement__c",
                            "VlocityRecordSourceKey": "%vlocity_namespace%__ObjectElement__c/34329484-b7c5-8658-d2ce-86409be1583d"
                        },
                        {
                            "%vlocity_namespace%__AttributeId__c": "",
                            "%vlocity_namespace%__Column__c": "1",
                            "%vlocity_namespace%__EffectiveFromDate__c": "",
                            "%vlocity_namespace%__EffectiveUntilDate__c": "",
                            "%vlocity_namespace%__FieldApiName__c": "",
                            "%vlocity_namespace%__GlobalKey__c": "c67d2530-165e-14b8-f2eb-cf71c4a46f1c",
                            "%vlocity_namespace%__IsActive__c": true,
                            "%vlocity_namespace%__IsRequired__c": false,
                            "%vlocity_namespace%__ObjectSectionId__c": {
                                "Name": "d70e6a55-00c1-2e49-c25b-8e1bf7c38aec",
                                "VlocityDataPackType": "VlocityMatchingKeyObject",
                                "VlocityMatchingRecordSourceKey": "%vlocity_namespace%__ObjectSection__c/d70e6a55-00c1-2e49-c25b-8e1bf7c38aec",
                                "VlocityRecordSObjectType": "%vlocity_namespace%__ObjectSection__c"
                            },
                            "%vlocity_namespace%__Sequence__c": 326,
                            "Name": "ATTRIBUTE-A270404",
                            "VlocityDataPackType": "SObject",
                            "VlocityRecordSObjectType": "%vlocity_namespace%__ObjectElement__c",
                            "VlocityRecordSourceKey": "%vlocity_namespace%__ObjectElement__c/c67d2530-165e-14b8-f2eb-cf71c4a46f1c"
                        },
                        {
                            "%vlocity_namespace%__AttributeId__c": "",
                            "%vlocity_namespace%__Column__c": "1",
                            "%vlocity_namespace%__EffectiveFromDate__c": "",
                            "%vlocity_namespace%__EffectiveUntilDate__c": "",
                            "%vlocity_namespace%__FieldApiName__c": "",
                            "%vlocity_namespace%__GlobalKey__c": "27e2909e-e22a-3c40-8f8e-2516d26ab2f8",
                            "%vlocity_namespace%__IsActive__c": true,
                            "%vlocity_namespace%__IsRequired__c": false,
                            "%vlocity_namespace%__ObjectSectionId__c": {
                                "Name": "d70e6a55-00c1-2e49-c25b-8e1bf7c38aec",
                                "VlocityDataPackType": "VlocityMatchingKeyObject",
                                "VlocityMatchingRecordSourceKey": "%vlocity_namespace%__ObjectSection__c/d70e6a55-00c1-2e49-c25b-8e1bf7c38aec",
                                "VlocityRecordSObjectType": "%vlocity_namespace%__ObjectSection__c"
                            },
                            "%vlocity_namespace%__Sequence__c": 327,
                            "Name": "ATTRIBUTE-A344782",
                            "VlocityDataPackType": "SObject",
                            "VlocityRecordSObjectType": "%vlocity_namespace%__ObjectElement__c",
                            "VlocityRecordSourceKey": "%vlocity_namespace%__ObjectElement__c/27e2909e-e22a-3c40-8f8e-2516d26ab2f8"
                        },
                        {
                            "%vlocity_namespace%__AttributeId__c": "",
                            "%vlocity_namespace%__Column__c": "1",
                            "%vlocity_namespace%__EffectiveFromDate__c": "",
                            "%vlocity_namespace%__EffectiveUntilDate__c": "",
                            "%vlocity_namespace%__FieldApiName__c": "",
                            "%vlocity_namespace%__GlobalKey__c": "5ecf2b76-b627-ea25-b959-0df5bf9c3835",
                            "%vlocity_namespace%__IsActive__c": true,
                            "%vlocity_namespace%__IsRequired__c": false,
                            "%vlocity_namespace%__ObjectSectionId__c": {
                                "Name": "d70e6a55-00c1-2e49-c25b-8e1bf7c38aec",
                                "VlocityDataPackType": "VlocityMatchingKeyObject",
                                "VlocityMatchingRecordSourceKey": "%vlocity_namespace%__ObjectSection__c/d70e6a55-00c1-2e49-c25b-8e1bf7c38aec",
                                "VlocityRecordSObjectType": "%vlocity_namespace%__ObjectSection__c"
                            },
                            "%vlocity_namespace%__Sequence__c": 328,
                            "Name": "ATTRIBUTE-B121142",
                            "VlocityDataPackType": "SObject",
                            "VlocityRecordSObjectType": "%vlocity_namespace%__ObjectElement__c",
                            "VlocityRecordSourceKey": "%vlocity_namespace%__ObjectElement__c/5ecf2b76-b627-ea25-b959-0df5bf9c3835"
                        },
                        {
                            "%vlocity_namespace%__AttributeId__c": "",
                            "%vlocity_namespace%__Column__c": "1",
                            "%vlocity_namespace%__EffectiveFromDate__c": "",
                            "%vlocity_namespace%__EffectiveUntilDate__c": "",
                            "%vlocity_namespace%__FieldApiName__c": "",
                            "%vlocity_namespace%__GlobalKey__c": "fb02cc26-219a-44ee-fe84-6664bed23e29",
                            "%vlocity_namespace%__IsActive__c": true,
                            "%vlocity_namespace%__IsRequired__c": false,
                            "%vlocity_namespace%__ObjectSectionId__c": {
                                "Name": "d70e6a55-00c1-2e49-c25b-8e1bf7c38aec",
                                "VlocityDataPackType": "VlocityMatchingKeyObject",
                                "VlocityMatchingRecordSourceKey": "%vlocity_namespace%__ObjectSection__c/d70e6a55-00c1-2e49-c25b-8e1bf7c38aec",
                                "VlocityRecordSObjectType": "%vlocity_namespace%__ObjectSection__c"
                            },
                            "%vlocity_namespace%__Sequence__c": 329,
                            "Name": "ATTRIBUTE-B223426",
                            "VlocityDataPackType": "SObject",
                            "VlocityRecordSObjectType": "%vlocity_namespace%__ObjectElement__c",
                            "VlocityRecordSourceKey": "%vlocity_namespace%__ObjectElement__c/fb02cc26-219a-44ee-fe84-6664bed23e29"
                        }
                    ],
                    "%vlocity_namespace%__ObjectFacetId__c": {
                        "Name": "6b91763f-40b4-b1ad-7434-6f4d14e6f14d",
                        "VlocityDataPackType": "VlocityMatchingKeyObject",
                        "VlocityMatchingRecordSourceKey": "%vlocity_namespace%__ObjectFacet__c/6b91763f-40b4-b1ad-7434-6f4d14e6f14d",
                        "VlocityRecordSObjectType": "%vlocity_namespace%__ObjectFacet__c"
                    },
                    "%vlocity_namespace%__SectionId__c": {
                        "%vlocity_namespace%__GlobalKey__c": "5ceff4783b0f59f31b27417a7064a12c",
                        "VlocityDataPackType": "VlocityLookupMatchingKeyObject",
                        "VlocityLookupRecordSourceKey": "%vlocity_namespace%__UISection__c/5ceff4783b0f59f31b27417a7064a12c",
                        "VlocityRecordSObjectType": "%vlocity_namespace%__UISection__c"
                    },
                    "%vlocity_namespace%__Sequence__c": 10,
                    "%vlocity_namespace%__TabKeyOrder__c": "Top-Down",
                    "%vlocity_namespace%__ViewType__c": "Field Layout",
                    "%vlocity_namespace%__ViewUri__c": "",
                    "Name": "d70e6a55-00c1-2e49-c25b-8e1bf7c38aec",
                    "VlocityDataPackType": "SObject",
                    "VlocityRecordSObjectType": "%vlocity_namespace%__ObjectSection__c",
                    "VlocityRecordSourceKey": "%vlocity_namespace%__ObjectSection__c/d70e6a55-00c1-2e49-c25b-8e1bf7c38aec"
                },
                {
                    "%vlocity_namespace%__ColumnLayout__c": "1 Column",
                    "%vlocity_namespace%__EffectiveFromDate__c": "",
                    "%vlocity_namespace%__EffectiveUntilDate__c": "",
                    "%vlocity_namespace%__GlobalKey__c": "9828b397-8ff0-2956-c2c4-5c80d2407630",
                    "%vlocity_namespace%__IsActive__c": true,
                    "%vlocity_namespace%__ObjectElement__c": [
                        {
                            "%vlocity_namespace%__AttributeId__c": "",
                            "%vlocity_namespace%__Column__c": "1",
                            "%vlocity_namespace%__EffectiveFromDate__c": "",
                            "%vlocity_namespace%__EffectiveUntilDate__c": "",
                            "%vlocity_namespace%__FieldApiName__c": "IsActive",
                            "%vlocity_namespace%__GlobalKey__c": "e6992165-1fdf-8b15-8500-357f647bf9e8",
                            "%vlocity_namespace%__IsActive__c": true,
                            "%vlocity_namespace%__IsRequired__c": false,
                            "%vlocity_namespace%__ObjectSectionId__c": {
                                "Name": "9828b397-8ff0-2956-c2c4-5c80d2407630",
                                "VlocityDataPackType": "VlocityMatchingKeyObject",
                                "VlocityMatchingRecordSourceKey": "%vlocity_namespace%__ObjectSection__c/9828b397-8ff0-2956-c2c4-5c80d2407630",
                                "VlocityRecordSObjectType": "%vlocity_namespace%__ObjectSection__c"
                            },
                            "%vlocity_namespace%__Sequence__c": 10,
                            "%vlocity_namespace%__Type__c": "Field",
                            "Name": "Active",
                            "VlocityDataPackType": "SObject",
                            "VlocityRecordSObjectType": "%vlocity_namespace%__ObjectElement__c",
                            "VlocityRecordSourceKey": "%vlocity_namespace%__ObjectElement__c/e6992165-1fdf-8b15-8500-357f647bf9e8"
                        },
                        {
                            "%vlocity_namespace%__AttributeId__c": "",
                            "%vlocity_namespace%__Column__c": "1",
                            "%vlocity_namespace%__EffectiveFromDate__c": "",
                            "%vlocity_namespace%__EffectiveUntilDate__c": "",
                            "%vlocity_namespace%__FieldApiName__c": "%vlocity_namespace%__SellingStartDate__c",
                            "%vlocity_namespace%__GlobalKey__c": "6e7c59ab-d865-baf0-316a-587d7c0a2b5d",
                            "%vlocity_namespace%__IsActive__c": true,
                            "%vlocity_namespace%__IsRequired__c": false,
                            "%vlocity_namespace%__ObjectSectionId__c": {
                                "Name": "9828b397-8ff0-2956-c2c4-5c80d2407630",
                                "VlocityDataPackType": "VlocityMatchingKeyObject",
                                "VlocityMatchingRecordSourceKey": "%vlocity_namespace%__ObjectSection__c/9828b397-8ff0-2956-c2c4-5c80d2407630",
                                "VlocityRecordSObjectType": "%vlocity_namespace%__ObjectSection__c"
                            },
                            "%vlocity_namespace%__Sequence__c": 20,
                            "%vlocity_namespace%__Type__c": "Field",
                            "Name": "Selling Start Date",
                            "VlocityDataPackType": "SObject",
                            "VlocityRecordSObjectType": "%vlocity_namespace%__ObjectElement__c",
                            "VlocityRecordSourceKey": "%vlocity_namespace%__ObjectElement__c/6e7c59ab-d865-baf0-316a-587d7c0a2b5d"
                        },
                        {
                            "%vlocity_namespace%__AttributeId__c": "",
                            "%vlocity_namespace%__Column__c": "1",
                            "%vlocity_namespace%__EffectiveFromDate__c": "",
                            "%vlocity_namespace%__EffectiveUntilDate__c": "",
                            "%vlocity_namespace%__FieldApiName__c": "%vlocity_namespace%__SellingEndDate__c",
                            "%vlocity_namespace%__GlobalKey__c": "6054701b-fb83-fd62-79f5-baf95a8d49f1",
                            "%vlocity_namespace%__IsActive__c": true,
                            "%vlocity_namespace%__IsRequired__c": false,
                            "%vlocity_namespace%__ObjectSectionId__c": {
                                "Name": "9828b397-8ff0-2956-c2c4-5c80d2407630",
                                "VlocityDataPackType": "VlocityMatchingKeyObject",
                                "VlocityMatchingRecordSourceKey": "%vlocity_namespace%__ObjectSection__c/9828b397-8ff0-2956-c2c4-5c80d2407630",
                                "VlocityRecordSObjectType": "%vlocity_namespace%__ObjectSection__c"
                            },
                            "%vlocity_namespace%__Sequence__c": 30,
                            "%vlocity_namespace%__Type__c": "Field",
                            "Name": "Selling End Date",
                            "VlocityDataPackType": "SObject",
                            "VlocityRecordSObjectType": "%vlocity_namespace%__ObjectElement__c",
                            "VlocityRecordSourceKey": "%vlocity_namespace%__ObjectElement__c/6054701b-fb83-fd62-79f5-baf95a8d49f1"
                        },
                        {
                            "%vlocity_namespace%__AttributeId__c": "",
                            "%vlocity_namespace%__Column__c": "1",
                            "%vlocity_namespace%__EffectiveFromDate__c": "",
                            "%vlocity_namespace%__EffectiveUntilDate__c": "",
                            "%vlocity_namespace%__FieldApiName__c": "%vlocity_namespace%__FulfilmentStartDate__c",
                            "%vlocity_namespace%__GlobalKey__c": "de3f64a9-43e2-b323-38f1-8a01f431f24f",
                            "%vlocity_namespace%__IsActive__c": true,
                            "%vlocity_namespace%__IsRequired__c": false,
                            "%vlocity_namespace%__ObjectSectionId__c": {
                                "Name": "9828b397-8ff0-2956-c2c4-5c80d2407630",
                                "VlocityDataPackType": "VlocityMatchingKeyObject",
                                "VlocityMatchingRecordSourceKey": "%vlocity_namespace%__ObjectSection__c/9828b397-8ff0-2956-c2c4-5c80d2407630",
                                "VlocityRecordSObjectType": "%vlocity_namespace%__ObjectSection__c"
                            },
                            "%vlocity_namespace%__Sequence__c": 40,
                            "%vlocity_namespace%__Type__c": "Field",
                            "Name": "Fulfilment Start Date",
                            "VlocityDataPackType": "SObject",
                            "VlocityRecordSObjectType": "%vlocity_namespace%__ObjectElement__c",
                            "VlocityRecordSourceKey": "%vlocity_namespace%__ObjectElement__c/de3f64a9-43e2-b323-38f1-8a01f431f24f"
                        },
                        {
                            "%vlocity_namespace%__AttributeId__c": "",
                            "%vlocity_namespace%__Column__c": "1",
                            "%vlocity_namespace%__EffectiveFromDate__c": "",
                            "%vlocity_namespace%__EffectiveUntilDate__c": "",
                            "%vlocity_namespace%__FieldApiName__c": "%vlocity_namespace%__EndOfLifeDate__c",
                            "%vlocity_namespace%__GlobalKey__c": "6dd9eced-c9f5-cd96-0441-f4d56c2a4e93",
                            "%vlocity_namespace%__IsActive__c": true,
                            "%vlocity_namespace%__IsRequired__c": false,
                            "%vlocity_namespace%__ObjectSectionId__c": {
                                "Name": "9828b397-8ff0-2956-c2c4-5c80d2407630",
                                "VlocityDataPackType": "VlocityMatchingKeyObject",
                                "VlocityMatchingRecordSourceKey": "%vlocity_namespace%__ObjectSection__c/9828b397-8ff0-2956-c2c4-5c80d2407630",
                                "VlocityRecordSObjectType": "%vlocity_namespace%__ObjectSection__c"
                            },
                            "%vlocity_namespace%__Sequence__c": 50,
                            "%vlocity_namespace%__Type__c": "Field",
                            "Name": "End of Life Date",
                            "VlocityDataPackType": "SObject",
                            "VlocityRecordSObjectType": "%vlocity_namespace%__ObjectElement__c",
                            "VlocityRecordSourceKey": "%vlocity_namespace%__ObjectElement__c/6dd9eced-c9f5-cd96-0441-f4d56c2a4e93"
                        }
                    ],
                    "%vlocity_namespace%__ObjectFacetId__c": {
                        "Name": "6b91763f-40b4-b1ad-7434-6f4d14e6f14d",
                        "VlocityDataPackType": "VlocityMatchingKeyObject",
                        "VlocityMatchingRecordSourceKey": "%vlocity_namespace%__ObjectFacet__c/6b91763f-40b4-b1ad-7434-6f4d14e6f14d",
                        "VlocityRecordSObjectType": "%vlocity_namespace%__ObjectFacet__c"
                    },
                    "%vlocity_namespace%__SectionId__c": {
                        "%vlocity_namespace%__GlobalKey__c": "07fb6c10c8822dcf5708e0b13836de9d",
                        "VlocityDataPackType": "VlocityLookupMatchingKeyObject",
                        "VlocityLookupRecordSourceKey": "%vlocity_namespace%__UISection__c/07fb6c10c8822dcf5708e0b13836de9d",
                        "VlocityRecordSObjectType": "%vlocity_namespace%__UISection__c"
                    },
                    "%vlocity_namespace%__Sequence__c": 20,
                    "%vlocity_namespace%__TabKeyOrder__c": "Top-Down",
                    "%vlocity_namespace%__ViewType__c": "Field Layout",
                    "%vlocity_namespace%__ViewUri__c": "",
                    "Name": "9828b397-8ff0-2956-c2c4-5c80d2407630",
                    "VlocityDataPackType": "SObject",
                    "VlocityRecordSObjectType": "%vlocity_namespace%__ObjectSection__c",
                    "VlocityRecordSourceKey": "%vlocity_namespace%__ObjectSection__c/9828b397-8ff0-2956-c2c4-5c80d2407630"
                }
            ],
            "%vlocity_namespace%__Sequence__c": 10,
            "Name": "6b91763f-40b4-b1ad-7434-6f4d14e6f14d",
            "VlocityDataPackType": "SObject",
            "VlocityRecordSObjectType": "%vlocity_namespace%__ObjectFacet__c",
            "VlocityRecordSourceKey": "%vlocity_namespace%__ObjectFacet__c/6b91763f-40b4-b1ad-7434-6f4d14e6f14d"
        },
        {
            "%vlocity_namespace%__EffectiveFromDate__c": "",
            "%vlocity_namespace%__EffectiveUntilDate__c": "",
            "%vlocity_namespace%__FacetId__c": {
                "%vlocity_namespace%__GlobalKey__c": "885e10262c2299afdcd1aa6e95138717",
                "VlocityDataPackType": "VlocityLookupMatchingKeyObject",
                "VlocityLookupRecordSourceKey": "%vlocity_namespace%__UIFacet__c/885e10262c2299afdcd1aa6e95138717",
                "VlocityRecordSObjectType": "%vlocity_namespace%__UIFacet__c"
            },
            "%vlocity_namespace%__GlobalKey__c": "0782ea99-bc70-29e4-b774-9f1c555f1cee",
            "%vlocity_namespace%__IsActive__c": true,
            "%vlocity_namespace%__ObjectLayoutId__c": {
                "%vlocity_namespace%__GlobalKey__c": "29ace50d-d6bb-77eb-35d9-21879b55b1ca",
                "VlocityDataPackType": "VlocityMatchingKeyObject",
                "VlocityMatchingRecordSourceKey": "%vlocity_namespace%__ObjectLayout__c/29ace50d-d6bb-77eb-35d9-21879b55b1ca",
                "VlocityRecordSObjectType": "%vlocity_namespace%__ObjectLayout__c"
            },
            "%vlocity_namespace%__ObjectSection__c": [
                {
                    "%vlocity_namespace%__ColumnLayout__c": "",
                    "%vlocity_namespace%__EffectiveFromDate__c": "",
                    "%vlocity_namespace%__EffectiveUntilDate__c": "",
                    "%vlocity_namespace%__GlobalKey__c": "51193271-9b26-d30d-3054-b1252fe092ce",
                    "%vlocity_namespace%__IsActive__c": true,
                    "%vlocity_namespace%__ObjectFacetId__c": {
                        "Name": "0782ea99-bc70-29e4-b774-9f1c555f1cee",
                        "VlocityDataPackType": "VlocityMatchingKeyObject",
                        "VlocityMatchingRecordSourceKey": "%vlocity_namespace%__ObjectFacet__c/0782ea99-bc70-29e4-b774-9f1c555f1cee",
                        "VlocityRecordSObjectType": "%vlocity_namespace%__ObjectFacet__c"
                    },
                    "%vlocity_namespace%__SectionId__c": {
                        "%vlocity_namespace%__GlobalKey__c": "885e10262c2299afdcd1aa6e95138717",
                        "VlocityDataPackType": "VlocityLookupMatchingKeyObject",
                        "VlocityLookupRecordSourceKey": "%vlocity_namespace%__UISection__c/885e10262c2299afdcd1aa6e95138717",
                        "VlocityRecordSObjectType": "%vlocity_namespace%__UISection__c"
                    },
                    "%vlocity_namespace%__Sequence__c": 10,
                    "%vlocity_namespace%__TabKeyOrder__c": "",
                    "%vlocity_namespace%__ViewType__c": "Custom View",
                    "%vlocity_namespace%__ViewUri__c": "VlocObjAttrsFields",
                    "Name": "51193271-9b26-d30d-3054-b1252fe092ce",
                    "VlocityDataPackType": "SObject",
                    "VlocityRecordSObjectType": "%vlocity_namespace%__ObjectSection__c",
                    "VlocityRecordSourceKey": "%vlocity_namespace%__ObjectSection__c/51193271-9b26-d30d-3054-b1252fe092ce"
                }
            ],
            "%vlocity_namespace%__Sequence__c": 20,
            "Name": "0782ea99-bc70-29e4-b774-9f1c555f1cee",
            "VlocityDataPackType": "SObject",
            "VlocityRecordSObjectType": "%vlocity_namespace%__ObjectFacet__c",
            "VlocityRecordSourceKey": "%vlocity_namespace%__ObjectFacet__c/0782ea99-bc70-29e4-b774-9f1c555f1cee"
        },
        {
            "%vlocity_namespace%__EffectiveFromDate__c": "",
            "%vlocity_namespace%__EffectiveUntilDate__c": "",
            "%vlocity_namespace%__FacetId__c": {
                "%vlocity_namespace%__GlobalKey__c": "7e2708aeb65763c54052f57ed1a1ec1d",
                "VlocityDataPackType": "VlocityLookupMatchingKeyObject",
                "VlocityLookupRecordSourceKey": "%vlocity_namespace%__UIFacet__c/7e2708aeb65763c54052f57ed1a1ec1d",
                "VlocityRecordSObjectType": "%vlocity_namespace%__UIFacet__c"
            },
            "%vlocity_namespace%__GlobalKey__c": "b4258c5b-a298-b1f6-7fb8-f39ababf4e74",
            "%vlocity_namespace%__IsActive__c": true,
            "%vlocity_namespace%__ObjectLayoutId__c": {
                "%vlocity_namespace%__GlobalKey__c": "29ace50d-d6bb-77eb-35d9-21879b55b1ca",
                "VlocityDataPackType": "VlocityMatchingKeyObject",
                "VlocityMatchingRecordSourceKey": "%vlocity_namespace%__ObjectLayout__c/29ace50d-d6bb-77eb-35d9-21879b55b1ca",
                "VlocityRecordSObjectType": "%vlocity_namespace%__ObjectLayout__c"
            },
            "%vlocity_namespace%__ObjectSection__c": [
                {
                    "%vlocity_namespace%__ColumnLayout__c": "",
                    "%vlocity_namespace%__EffectiveFromDate__c": "",
                    "%vlocity_namespace%__EffectiveUntilDate__c": "",
                    "%vlocity_namespace%__GlobalKey__c": "f376429e-2b50-4203-0729-1588ae6355f1",
                    "%vlocity_namespace%__IsActive__c": true,
                    "%vlocity_namespace%__ObjectFacetId__c": {
                        "Name": "b4258c5b-a298-b1f6-7fb8-f39ababf4e74",
                        "VlocityDataPackType": "VlocityMatchingKeyObject",
                        "VlocityMatchingRecordSourceKey": "%vlocity_namespace%__ObjectFacet__c/b4258c5b-a298-b1f6-7fb8-f39ababf4e74",
                        "VlocityRecordSObjectType": "%vlocity_namespace%__ObjectFacet__c"
                    },
                    "%vlocity_namespace%__SectionId__c": {
                        "%vlocity_namespace%__GlobalKey__c": "7e2708aeb65763c54052f57ed1a1ec1d",
                        "VlocityDataPackType": "VlocityLookupMatchingKeyObject",
                        "VlocityLookupRecordSourceKey": "%vlocity_namespace%__UISection__c/7e2708aeb65763c54052f57ed1a1ec1d",
                        "VlocityRecordSObjectType": "%vlocity_namespace%__UISection__c"
                    },
                    "%vlocity_namespace%__Sequence__c": 10,
                    "%vlocity_namespace%__TabKeyOrder__c": "",
                    "%vlocity_namespace%__ViewType__c": "Custom View",
                    "%vlocity_namespace%__ViewUri__c": "Attachments",
                    "Name": "f376429e-2b50-4203-0729-1588ae6355f1",
                    "VlocityDataPackType": "SObject",
                    "VlocityRecordSObjectType": "%vlocity_namespace%__ObjectSection__c",
                    "VlocityRecordSourceKey": "%vlocity_namespace%__ObjectSection__c/f376429e-2b50-4203-0729-1588ae6355f1"
                }
            ],
            "%vlocity_namespace%__Sequence__c": 30,
            "Name": "b4258c5b-a298-b1f6-7fb8-f39ababf4e74",
            "VlocityDataPackType": "SObject",
            "VlocityRecordSObjectType": "%vlocity_namespace%__ObjectFacet__c",
            "VlocityRecordSourceKey": "%vlocity_namespace%__ObjectFacet__c/b4258c5b-a298-b1f6-7fb8-f39ababf4e74"
        },
        {
            "%vlocity_namespace%__EffectiveFromDate__c": "",
            "%vlocity_namespace%__EffectiveUntilDate__c": "",
            "%vlocity_namespace%__FacetId__c": {
                "%vlocity_namespace%__GlobalKey__c": "88133f31931c2d3463baa8f14230978f",
                "VlocityDataPackType": "VlocityLookupMatchingKeyObject",
                "VlocityLookupRecordSourceKey": "%vlocity_namespace%__UIFacet__c/88133f31931c2d3463baa8f14230978f",
                "VlocityRecordSObjectType": "%vlocity_namespace%__UIFacet__c"
            },
            "%vlocity_namespace%__GlobalKey__c": "4bd07664-31d6-a829-5418-de3eff5e1fb2",
            "%vlocity_namespace%__IsActive__c": true,
            "%vlocity_namespace%__ObjectLayoutId__c": {
                "%vlocity_namespace%__GlobalKey__c": "29ace50d-d6bb-77eb-35d9-21879b55b1ca",
                "VlocityDataPackType": "VlocityMatchingKeyObject",
                "VlocityMatchingRecordSourceKey": "%vlocity_namespace%__ObjectLayout__c/29ace50d-d6bb-77eb-35d9-21879b55b1ca",
                "VlocityRecordSObjectType": "%vlocity_namespace%__ObjectLayout__c"
            },
            "%vlocity_namespace%__ObjectSection__c": [
                {
                    "%vlocity_namespace%__ColumnLayout__c": "",
                    "%vlocity_namespace%__EffectiveFromDate__c": "",
                    "%vlocity_namespace%__EffectiveUntilDate__c": "",
                    "%vlocity_namespace%__GlobalKey__c": "3acfba7b-1dd2-70ea-e49e-61688ffda57d",
                    "%vlocity_namespace%__IsActive__c": true,
                    "%vlocity_namespace%__ObjectFacetId__c": {
                        "Name": "4bd07664-31d6-a829-5418-de3eff5e1fb2",
                        "VlocityDataPackType": "VlocityMatchingKeyObject",
                        "VlocityMatchingRecordSourceKey": "%vlocity_namespace%__ObjectFacet__c/4bd07664-31d6-a829-5418-de3eff5e1fb2",
                        "VlocityRecordSObjectType": "%vlocity_namespace%__ObjectFacet__c"
                    },
                    "%vlocity_namespace%__SectionId__c": {
                        "%vlocity_namespace%__GlobalKey__c": "88133f31931c2d3463baa8f14230978f",
                        "VlocityDataPackType": "VlocityLookupMatchingKeyObject",
                        "VlocityLookupRecordSourceKey": "%vlocity_namespace%__UISection__c/88133f31931c2d3463baa8f14230978f",
                        "VlocityRecordSObjectType": "%vlocity_namespace%__UISection__c"
                    },
                    "%vlocity_namespace%__Sequence__c": 10,
                    "%vlocity_namespace%__TabKeyOrder__c": "",
                    "%vlocity_namespace%__ViewType__c": "Custom View",
                    "%vlocity_namespace%__ViewUri__c": "ProductStructure",
                    "Name": "3acfba7b-1dd2-70ea-e49e-61688ffda57d",
                    "VlocityDataPackType": "SObject",
                    "VlocityRecordSObjectType": "%vlocity_namespace%__ObjectSection__c",
                    "VlocityRecordSourceKey": "%vlocity_namespace%__ObjectSection__c/3acfba7b-1dd2-70ea-e49e-61688ffda57d"
                }
            ],
            "%vlocity_namespace%__Sequence__c": 40,
            "Name": "4bd07664-31d6-a829-5418-de3eff5e1fb2",
            "VlocityDataPackType": "SObject",
            "VlocityRecordSObjectType": "%vlocity_namespace%__ObjectFacet__c",
            "VlocityRecordSourceKey": "%vlocity_namespace%__ObjectFacet__c/4bd07664-31d6-a829-5418-de3eff5e1fb2"
        },
        {
            "%vlocity_namespace%__EffectiveFromDate__c": "",
            "%vlocity_namespace%__EffectiveUntilDate__c": "",
            "%vlocity_namespace%__FacetId__c": {
                "%vlocity_namespace%__GlobalKey__c": "e22ac25b066b201473de7aa700ef5d92",
                "VlocityDataPackType": "VlocityLookupMatchingKeyObject",
                "VlocityLookupRecordSourceKey": "%vlocity_namespace%__UIFacet__c/e22ac25b066b201473de7aa700ef5d92",
                "VlocityRecordSObjectType": "%vlocity_namespace%__UIFacet__c"
            },
            "%vlocity_namespace%__GlobalKey__c": "671de531-4234-7132-659c-cc1d8695b41b",
            "%vlocity_namespace%__IsActive__c": true,
            "%vlocity_namespace%__ObjectLayoutId__c": {
                "%vlocity_namespace%__GlobalKey__c": "29ace50d-d6bb-77eb-35d9-21879b55b1ca",
                "VlocityDataPackType": "VlocityMatchingKeyObject",
                "VlocityMatchingRecordSourceKey": "%vlocity_namespace%__ObjectLayout__c/29ace50d-d6bb-77eb-35d9-21879b55b1ca",
                "VlocityRecordSObjectType": "%vlocity_namespace%__ObjectLayout__c"
            },
            "%vlocity_namespace%__ObjectSection__c": [
                {
                    "%vlocity_namespace%__ColumnLayout__c": "",
                    "%vlocity_namespace%__EffectiveFromDate__c": "",
                    "%vlocity_namespace%__EffectiveUntilDate__c": "",
                    "%vlocity_namespace%__GlobalKey__c": "e5a3dbfb-4fd5-37d0-664f-57bb78733335",
                    "%vlocity_namespace%__IsActive__c": true,
                    "%vlocity_namespace%__ObjectFacetId__c": {
                        "Name": "671de531-4234-7132-659c-cc1d8695b41b",
                        "VlocityDataPackType": "VlocityMatchingKeyObject",
                        "VlocityMatchingRecordSourceKey": "%vlocity_namespace%__ObjectFacet__c/671de531-4234-7132-659c-cc1d8695b41b",
                        "VlocityRecordSObjectType": "%vlocity_namespace%__ObjectFacet__c"
                    },
                    "%vlocity_namespace%__SectionId__c": {
                        "%vlocity_namespace%__GlobalKey__c": "e22ac25b066b201473de7aa700ef5d92",
                        "VlocityDataPackType": "VlocityLookupMatchingKeyObject",
                        "VlocityLookupRecordSourceKey": "%vlocity_namespace%__UISection__c/e22ac25b066b201473de7aa700ef5d92",
                        "VlocityRecordSObjectType": "%vlocity_namespace%__UISection__c"
                    },
                    "%vlocity_namespace%__Sequence__c": 10,
                    "%vlocity_namespace%__TabKeyOrder__c": "",
                    "%vlocity_namespace%__ViewType__c": "Custom View",
                    "%vlocity_namespace%__ViewUri__c": "ObjectPricing",
                    "Name": "e5a3dbfb-4fd5-37d0-664f-57bb78733335",
                    "VlocityDataPackType": "SObject",
                    "VlocityRecordSObjectType": "%vlocity_namespace%__ObjectSection__c",
                    "VlocityRecordSourceKey": "%vlocity_namespace%__ObjectSection__c/e5a3dbfb-4fd5-37d0-664f-57bb78733335"
                }
            ],
            "%vlocity_namespace%__Sequence__c": 50,
            "Name": "671de531-4234-7132-659c-cc1d8695b41b",
            "VlocityDataPackType": "SObject",
            "VlocityRecordSObjectType": "%vlocity_namespace%__ObjectFacet__c",
            "VlocityRecordSourceKey": "%vlocity_namespace%__ObjectFacet__c/671de531-4234-7132-659c-cc1d8695b41b"
        },
        {
            "%vlocity_namespace%__EffectiveFromDate__c": "",
            "%vlocity_namespace%__EffectiveUntilDate__c": "",
            "%vlocity_namespace%__FacetId__c": {
                "%vlocity_namespace%__GlobalKey__c": "f3ace7a9322ba258081738b2a79fb02a",
                "VlocityDataPackType": "VlocityLookupMatchingKeyObject",
                "VlocityLookupRecordSourceKey": "%vlocity_namespace%__UIFacet__c/f3ace7a9322ba258081738b2a79fb02a",
                "VlocityRecordSObjectType": "%vlocity_namespace%__UIFacet__c"
            },
            "%vlocity_namespace%__GlobalKey__c": "ed2b561a-70d3-1dd4-a65e-dfda35b91cd8",
            "%vlocity_namespace%__IsActive__c": true,
            "%vlocity_namespace%__ObjectLayoutId__c": {
                "%vlocity_namespace%__GlobalKey__c": "29ace50d-d6bb-77eb-35d9-21879b55b1ca",
                "VlocityDataPackType": "VlocityMatchingKeyObject",
                "VlocityMatchingRecordSourceKey": "%vlocity_namespace%__ObjectLayout__c/29ace50d-d6bb-77eb-35d9-21879b55b1ca",
                "VlocityRecordSObjectType": "%vlocity_namespace%__ObjectLayout__c"
            },
            "%vlocity_namespace%__ObjectSection__c": [
                {
                    "%vlocity_namespace%__ColumnLayout__c": "",
                    "%vlocity_namespace%__EffectiveFromDate__c": "",
                    "%vlocity_namespace%__EffectiveUntilDate__c": "",
                    "%vlocity_namespace%__GlobalKey__c": "caaa5456-087f-8b07-70fc-5cd165b5b7e1",
                    "%vlocity_namespace%__IsActive__c": true,
                    "%vlocity_namespace%__ObjectFacetId__c": {
                        "Name": "ed2b561a-70d3-1dd4-a65e-dfda35b91cd8",
                        "VlocityDataPackType": "VlocityMatchingKeyObject",
                        "VlocityMatchingRecordSourceKey": "%vlocity_namespace%__ObjectFacet__c/ed2b561a-70d3-1dd4-a65e-dfda35b91cd8",
                        "VlocityRecordSObjectType": "%vlocity_namespace%__ObjectFacet__c"
                    },
                    "%vlocity_namespace%__SectionId__c": {
                        "%vlocity_namespace%__GlobalKey__c": "f3ace7a9322ba258081738b2a79fb02a",
                        "VlocityDataPackType": "VlocityLookupMatchingKeyObject",
                        "VlocityLookupRecordSourceKey": "%vlocity_namespace%__UISection__c/f3ace7a9322ba258081738b2a79fb02a",
                        "VlocityRecordSObjectType": "%vlocity_namespace%__UISection__c"
                    },
                    "%vlocity_namespace%__Sequence__c": 10,
                    "%vlocity_namespace%__TabKeyOrder__c": "",
                    "%vlocity_namespace%__ViewType__c": "Custom View",
                    "%vlocity_namespace%__ViewUri__c": "ContextRules",
                    "Name": "caaa5456-087f-8b07-70fc-5cd165b5b7e1",
                    "VlocityDataPackType": "SObject",
                    "VlocityRecordSObjectType": "%vlocity_namespace%__ObjectSection__c",
                    "VlocityRecordSourceKey": "%vlocity_namespace%__ObjectSection__c/caaa5456-087f-8b07-70fc-5cd165b5b7e1"
                }
            ],
            "%vlocity_namespace%__Sequence__c": 60,
            "Name": "ed2b561a-70d3-1dd4-a65e-dfda35b91cd8",
            "VlocityDataPackType": "SObject",
            "VlocityRecordSObjectType": "%vlocity_namespace%__ObjectFacet__c",
            "VlocityRecordSourceKey": "%vlocity_namespace%__ObjectFacet__c/ed2b561a-70d3-1dd4-a65e-dfda35b91cd8"
        },
        {
            "%vlocity_namespace%__EffectiveFromDate__c": "",
            "%vlocity_namespace%__EffectiveUntilDate__c": "",
            "%vlocity_namespace%__FacetId__c": {
                "%vlocity_namespace%__GlobalKey__c": "dfe7bc9608d6f84ba04f9010be4bb8d1",
                "VlocityDataPackType": "VlocityLookupMatchingKeyObject",
                "VlocityLookupRecordSourceKey": "%vlocity_namespace%__UIFacet__c/dfe7bc9608d6f84ba04f9010be4bb8d1",
                "VlocityRecordSObjectType": "%vlocity_namespace%__UIFacet__c"
            },
            "%vlocity_namespace%__GlobalKey__c": "364bb03f-93d0-4bab-d0d7-14b76728e4ea",
            "%vlocity_namespace%__IsActive__c": true,
            "%vlocity_namespace%__ObjectLayoutId__c": {
                "%vlocity_namespace%__GlobalKey__c": "29ace50d-d6bb-77eb-35d9-21879b55b1ca",
                "VlocityDataPackType": "VlocityMatchingKeyObject",
                "VlocityMatchingRecordSourceKey": "%vlocity_namespace%__ObjectLayout__c/29ace50d-d6bb-77eb-35d9-21879b55b1ca",
                "VlocityRecordSObjectType": "%vlocity_namespace%__ObjectLayout__c"
            },
            "%vlocity_namespace%__ObjectSection__c": [
                {
                    "%vlocity_namespace%__ColumnLayout__c": "",
                    "%vlocity_namespace%__EffectiveFromDate__c": "",
                    "%vlocity_namespace%__EffectiveUntilDate__c": "",
                    "%vlocity_namespace%__GlobalKey__c": "eb3ac045-f186-e457-149c-6a323e64c67b",
                    "%vlocity_namespace%__IsActive__c": true,
                    "%vlocity_namespace%__ObjectFacetId__c": {
                        "Name": "364bb03f-93d0-4bab-d0d7-14b76728e4ea",
                        "VlocityDataPackType": "VlocityMatchingKeyObject",
                        "VlocityMatchingRecordSourceKey": "%vlocity_namespace%__ObjectFacet__c/364bb03f-93d0-4bab-d0d7-14b76728e4ea",
                        "VlocityRecordSObjectType": "%vlocity_namespace%__ObjectFacet__c"
                    },
                    "%vlocity_namespace%__SectionId__c": {
                        "%vlocity_namespace%__GlobalKey__c": "dfe7bc9608d6f84ba04f9010be4bb8d1",
                        "VlocityDataPackType": "VlocityLookupMatchingKeyObject",
                        "VlocityLookupRecordSourceKey": "%vlocity_namespace%__UISection__c/dfe7bc9608d6f84ba04f9010be4bb8d1",
                        "VlocityRecordSObjectType": "%vlocity_namespace%__UISection__c"
                    },
                    "%vlocity_namespace%__Sequence__c": 10,
                    "%vlocity_namespace%__TabKeyOrder__c": "",
                    "%vlocity_namespace%__ViewType__c": "Custom View",
                    "%vlocity_namespace%__ViewUri__c": "LayoutManagement",
                    "Name": "eb3ac045-f186-e457-149c-6a323e64c67b",
                    "VlocityDataPackType": "SObject",
                    "VlocityRecordSObjectType": "%vlocity_namespace%__ObjectSection__c",
                    "VlocityRecordSourceKey": "%vlocity_namespace%__ObjectSection__c/eb3ac045-f186-e457-149c-6a323e64c67b"
                }
            ],
            "%vlocity_namespace%__Sequence__c": 70,
            "Name": "364bb03f-93d0-4bab-d0d7-14b76728e4ea",
            "VlocityDataPackType": "SObject",
            "VlocityRecordSObjectType": "%vlocity_namespace%__ObjectFacet__c",
            "VlocityRecordSourceKey": "%vlocity_namespace%__ObjectFacet__c/364bb03f-93d0-4bab-d0d7-14b76728e4ea"
        }
    ],
    "%vlocity_namespace%__SubclassId__c": "01t8Y00000O12lTQAR",
    "Name": "Self-(Inherited)Layout-a2W5w000009KVoHEAW",
    "VlocityDataPackType": "SObject",
    "VlocityRecordSObjectType": "%vlocity_namespace%__ObjectLayout__c",
    "VlocityRecordSourceKey": "%vlocity_namespace%__ObjectLayout__c/29ace50d-d6bb-77eb-35d9-21879b55b1ca"
}