{
    "dataSource": {
        "contextVariables": [
        ],
        "orderBy": {
        },
        "type": null,
        "value": {
        }
    },
    "enableLwc": true,
    "isFlex": true,
    "lwc": {
        "DeveloperName": "cfDemo_account_actions_account_1_DE",
        "Id": "0Rb5Y000000ImeZSAS",
        "MasterLabel": "cfDemo_account_actions_account_1_DE",
        "NamespacePrefix": "c"
    },
    "states": [
        {
            "actions": [
            ],
            "childCards": [
            ],
            "components": {
                "layer-0": {
                    "children": [
                        {
                            "children": [
                                {
                                    "class": "slds-col ",
                                    "element": "outputField",
                                    "elementLabel": "Block-0-Text-0",
                                    "key": "element_element_block_0_0_outputField_0_0",
                                    "name": "Text",
                                    "parentElementKey": "element_block_0_0",
                                    "property": {
                                        "card": "{card}",
                                        "mergeField": "%3Cdiv%20class=%22slds-text-heading_small%22%3E%3Cspan%20style=%22font-size:%2012pt;%22%3E%3Cstrong%3EManage%20Your%20Account%3C/strong%3E%3C/span%3E%3C/div%3E",
                                        "record": "{record}"
                                    },
                                    "size": {
                                        "default": "12",
                                        "isResponsive": false
                                    },
                                    "stateIndex": 0,
                                    "styleObject": {
                                        "background": {
                                            "color": "",
                                            "image": "",
                                            "position": "",
                                            "repeat": "",
                                            "size": ""
                                        },
                                        "border": {
                                            "color": "",
                                            "radius": "",
                                            "style": "",
                                            "type": "",
                                            "width": ""
                                        },
                                        "class": "slds-p-bottom_xx-small slds-m-vertical_xx-small ",
                                        "container": {
                                            "class": ""
                                        },
                                        "elementStyleProperties": {
                                        },
                                        "inlineStyle": "",
                                        "margin": [
                                            {
                                                "label": "vertical:xx-small",
                                                "size": "xx-small",
                                                "type": "vertical"
                                            }
                                        ],
                                        "padding": [
                                            {
                                                "label": "bottom:xx-small",
                                                "size": "xx-small",
                                                "type": "bottom"
                                            }
                                        ],
                                        "selectedStyles": "action-link-header",
                                        "size": {
                                            "default": "12",
                                            "isResponsive": false
                                        },
                                        "sizeClass": "slds-size_12-of-12 ",
                                        "style": "            color:#666; ",
                                        "text": {
                                            "align": "",
                                            "color": "#666"
                                        }
                                    },
                                    "type": "text"
                                },
                                {
                                    "class": "slds-col ",
                                    "element": "action",
                                    "elementLabel": "Block-0-Action-1",
                                    "key": "element_element_block_0_0_action_1_0",
                                    "name": "Action",
                                    "parentElementKey": "element_block_0_0",
                                    "property": {
                                        "card": "{card}",
                                        "hideActionIcon": true,
                                        "record": "{record}",
                                        "stateAction": {
                                            "Web Page": {
                                                "targetName": "/apex"
                                            },
                                            "displayName": "Change Your Address",
                                            "id": "flex-action-1617051653240",
                                            "openUrlIn": "Current Window",
                                            "targetType": "Web Page",
                                            "type": "Custom",
                                            "vlocityIcon": "standard-default"
                                        },
                                        "stateObj": "{record}",
                                        "styles": {
                                            "label": {
                                                "color": "#3265AD",
                                                "fontSize": ".75rem"
                                            }
                                        }
                                    },
                                    "size": {
                                        "default": "12",
                                        "isResponsive": false
                                    },
                                    "stateIndex": 0,
                                    "styleObject": {
                                        "background": {
                                            "color": "",
                                            "image": "",
                                            "position": "",
                                            "repeat": "",
                                            "size": ""
                                        },
                                        "border": {
                                            "color": "",
                                            "radius": "",
                                            "style": "",
                                            "type": "",
                                            "width": ""
                                        },
                                        "class": "slds-p-vertical_xx-small slds-m-top_xx-small ",
                                        "container": {
                                            "class": ""
                                        },
                                        "elementStyleProperties": {
                                            "styles": {
                                                "label": {
                                                    "color": "#3265AD",
                                                    "fontSize": ".75rem"
                                                }
                                            }
                                        },
                                        "inlineStyle": "",
                                        "margin": [
                                            {
                                                "label": "top:xx-small",
                                                "size": "xx-small",
                                                "type": "top"
                                            }
                                        ],
                                        "padding": [
                                            {
                                                "label": "vertical:xx-small",
                                                "size": "xx-small",
                                                "type": "vertical"
                                            }
                                        ],
                                        "selectedStyles": "action-link",
                                        "size": {
                                            "default": "12",
                                            "isResponsive": false
                                        },
                                        "sizeClass": "slds-size_12-of-12 ",
                                        "style": "             ",
                                        "text": {
                                            "align": "",
                                            "color": ""
                                        }
                                    },
                                    "type": "element"
                                },
                                {
                                    "class": "slds-col ",
                                    "element": "action",
                                    "elementLabel": "Block-0-Action-2",
                                    "key": "element_element_block_0_0_action_2_0",
                                    "name": "Action",
                                    "parentElementKey": "element_block_0_0",
                                    "property": {
                                        "card": "{card}",
                                        "hideActionIcon": true,
                                        "record": "{record}",
                                        "stateAction": {
                                            "Web Page": {
                                                "targetName": "/apex"
                                            },
                                            "displayName": "Change Contact Information",
                                            "id": "flex-action-1617051663929",
                                            "openUrlIn": "Current Window",
                                            "targetType": "Web Page",
                                            "type": "Custom",
                                            "vlocityIcon": "standard-default"
                                        },
                                        "stateObj": "{record}",
                                        "styles": {
                                            "label": {
                                                "color": "#3265AD",
                                                "fontSize": ".75rem"
                                            }
                                        }
                                    },
                                    "size": {
                                        "default": "12",
                                        "isResponsive": false
                                    },
                                    "stateIndex": 0,
                                    "styleObject": {
                                        "background": {
                                            "color": "",
                                            "image": "",
                                            "position": "",
                                            "repeat": "",
                                            "size": ""
                                        },
                                        "border": {
                                            "color": "",
                                            "radius": "",
                                            "style": "",
                                            "type": "",
                                            "width": ""
                                        },
                                        "class": "slds-p-vertical_xx-small slds-m-top_xx-small ",
                                        "container": {
                                            "class": ""
                                        },
                                        "elementStyleProperties": {
                                            "styles": {
                                                "label": {
                                                    "color": "#3265AD",
                                                    "fontSize": ".75rem"
                                                }
                                            }
                                        },
                                        "inlineStyle": "",
                                        "margin": [
                                            {
                                                "label": "top:xx-small",
                                                "size": "xx-small",
                                                "type": "top"
                                            }
                                        ],
                                        "padding": [
                                            {
                                                "label": "vertical:xx-small",
                                                "size": "xx-small",
                                                "type": "vertical"
                                            }
                                        ],
                                        "selectedStyles": "action-link",
                                        "size": {
                                            "default": "12",
                                            "isResponsive": false
                                        },
                                        "sizeClass": "slds-size_12-of-12 ",
                                        "style": "             ",
                                        "text": {
                                            "align": "",
                                            "color": ""
                                        }
                                    },
                                    "type": "element"
                                },
                                {
                                    "class": "slds-col ",
                                    "element": "action",
                                    "elementLabel": "AccountActions-Action-2-clone-0",
                                    "key": "element_element_block_0_0_action_3_0",
                                    "name": "Action",
                                    "parentElementKey": "element_block_0_0",
                                    "property": {
                                        "card": "{card}",
                                        "hideActionIcon": true,
                                        "record": "{record}",
                                        "stateAction": {
                                            "Web Page": {
                                                "targetName": "/apex"
                                            },
                                            "displayName": "Communication Preferences",
                                            "id": "flex-action-1617051677486",
                                            "openUrlIn": "Current Window",
                                            "targetType": "Web Page",
                                            "type": "Custom",
                                            "vlocityIcon": "standard-default"
                                        },
                                        "stateObj": "{record}",
                                        "styles": {
                                            "label": {
                                                "color": "#3265AD",
                                                "fontSize": ".75rem"
                                            }
                                        }
                                    },
                                    "size": {
                                        "default": "12",
                                        "isResponsive": false
                                    },
                                    "stateIndex": 0,
                                    "styleObject": {
                                        "background": {
                                            "color": "",
                                            "image": "",
                                            "position": "",
                                            "repeat": "",
                                            "size": ""
                                        },
                                        "border": {
                                            "color": "",
                                            "radius": "",
                                            "style": "",
                                            "type": "",
                                            "width": ""
                                        },
                                        "class": "slds-p-vertical_xx-small slds-m-top_xx-small ",
                                        "container": {
                                            "class": ""
                                        },
                                        "elementStyleProperties": {
                                            "styles": {
                                                "label": {
                                                    "color": "#3265AD",
                                                    "fontSize": ".75rem"
                                                }
                                            }
                                        },
                                        "inlineStyle": "",
                                        "margin": [
                                            {
                                                "label": "top:xx-small",
                                                "size": "xx-small",
                                                "type": "top"
                                            }
                                        ],
                                        "padding": [
                                            {
                                                "label": "vertical:xx-small",
                                                "size": "xx-small",
                                                "type": "vertical"
                                            }
                                        ],
                                        "selectedStyles": "action-link",
                                        "size": {
                                            "default": "12",
                                            "isResponsive": false
                                        },
                                        "sizeClass": "slds-size_12-of-12 ",
                                        "style": "             ",
                                        "text": {
                                            "align": "",
                                            "color": ""
                                        }
                                    },
                                    "type": "element"
                                }
                            ],
                            "class": "slds-col ",
                            "element": "block",
                            "elementLabel": "AccountActions",
                            "name": "Block",
                            "property": {
                                "card": "{card}",
                                "collapsedByDefault": false,
                                "collapsible": false,
                                "label": "Block",
                                "record": "{record}"
                            },
                            "size": {
                                "default": "12",
                                "isResponsive": false
                            },
                            "stateIndex": 0,
                            "styleObject": {
                                "background": {
                                    "color": "#fff",
                                    "image": "",
                                    "position": "",
                                    "repeat": "",
                                    "size": ""
                                },
                                "border": {
                                    "color": "",
                                    "radius": "",
                                    "style": "none",
                                    "type": "",
                                    "width": ""
                                },
                                "class": "slds-p-around_medium ",
                                "container": {
                                    "class": ""
                                },
                                "elementStyleProperties": {
                                },
                                "inlineStyle": "box-shadow: rgb(0 0 0 / 16%) 0px 0px 6px 0px;",
                                "margin": [
                                ],
                                "padding": [
                                    {
                                        "label": "around:medium",
                                        "size": "medium",
                                        "type": "around"
                                    }
                                ],
                                "selectedStyles": "action-link-block",
                                "size": {
                                    "default": "12",
                                    "isResponsive": false
                                },
                                "sizeClass": "slds-size_12-of-12 ",
                                "style": "background-color:#fff;        border-style:none;     box-shadow: rgb(0 0 0 / 16%) 0px 0px 6px 0px;",
                                "text": {
                                    "align": "",
                                    "color": ""
                                }
                            },
                            "type": "block",
                            "userUpdatedElementLabel": true
                        }
                    ]
                }
            },
            "conditions": {
                "group": [
                ],
                "id": "state-condition-object",
                "isParent": true
            },
            "definedActions": {
                "actions": [
                ]
            },
            "fields": [
            ],
            "isSmartAction": false,
            "name": "Active",
            "omniscripts": [
            ],
            "smartAction": {
            },
            "styleObject": {
                "background": {
                    "color": "",
                    "image": "",
                    "position": "",
                    "repeat": "",
                    "size": ""
                },
                "border": {
                    "color": "",
                    "radius": "",
                    "style": "",
                    "type": "",
                    "width": ""
                },
                "class": "slds-card slds-p-around_x-small slds-m-bottom_x-small ",
                "container": {
                    "class": "slds-card"
                },
                "elementStyleProperties": {
                },
                "inlineStyle": "background-color: transparent; border: none;",
                "margin": [
                    {
                        "label": "bottom:x-small",
                        "size": "x-small",
                        "type": "bottom"
                    }
                ],
                "padding": [
                    {
                        "label": "around:x-small",
                        "size": "x-small",
                        "type": "around"
                    }
                ],
                "selectedStyles": "transparent-container",
                "size": {
                    "default": "12",
                    "isResponsive": false
                },
                "sizeClass": "slds-size_12-of-12 ",
                "style": "             background-color: transparent; border: none;",
                "text": {
                    "align": "",
                    "color": ""
                }
            }
        }
    ],
    "theme": "slds",
    "title": "demo_account_actions_account"
}